UVANewsApiModule/UVA_news_api.py
UVANewsApiModule/__init__.py
UVANewsApiModule/api_utility.py
UVANewsApiModule/test.py
UVANewsApiModule-0.0.4.dist-info/METADATA
UVANewsApiModule-0.0.4.dist-info/WHEEL
UVANewsApiModule-0.0.4.dist-info/top_level.txt
UVANewsApiModule-0.0.4.dist-info/RECORD
