Metadata-Version: 2.1
Name: UVANewsApiModule
Version: 0.0.4
Summary: API for news from the University of Virginia's website
Author: Benjamin Pusch
Author-email: benjaminpusch03@gmail.com
Keywords: python
Classifier: Development Status :: 3 - Alpha
Classifier: Intended Audience :: Education
Classifier: Programming Language :: Python :: 3
Classifier: Operating System :: MacOS :: MacOS X
Classifier: Operating System :: Microsoft :: Windows
Requires-Dist: asyncio
Requires-Dist: aiohttp
Requires-Dist: requests
Requires-Dist: datetime
